datamorphairflow/__init__.py
datamorphairflow/__version__.py
datamorphairflow/config_utils.py
datamorphairflow/datamorph_constants.py
datamorphairflow/file_util.py
datamorphairflow/helper_classes.py
datamorphairflow/hooks.py
datamorphairflow/utils.py
datamorphairflow/workflow_dag_builder.py
datamorphairflow/workflow_dag_factory.py
datamorphairflow/actions/__init__.py
datamorphairflow/actions/bash.py
datamorphairflow/actions/branch.py
datamorphairflow/actions/databricks.py
datamorphairflow/actions/email.py
datamorphairflow/actions/empty.py
datamorphairflow/actions/glue.py
datamorphairflow/actions/javajar.py
datamorphairflow/actions/loadparams.py
datamorphairflow/actions/markdag.py
datamorphairflow/actions/workflow_custom_operators.py
datamorphairflow/templates/__init__.py
datamorphairflow/templates/python_callable_template.py
datamorph_airflow-0.0.98.dist-info/METADATA
datamorph_airflow-0.0.98.dist-info/WHEEL
datamorph_airflow-0.0.98.dist-info/top_level.txt
datamorph_airflow-0.0.98.dist-info/RECORD
