Metadata-Version: 2.4
Name: datamorph-airflow
Version: 0.0.98
Summary: DataMorph's application to dynamically build Airflow DAGs from JSON files 
Author: Annapurna Annadatha
Author-email: sowmya@kwartile.com
License: MIT
Keywords: airflow
Classifier: License :: OSI Approved :: MIT License
Classifier: Programming Language :: Python
Classifier: Programming Language :: Python :: 3
Classifier: Programming Language :: Python :: 3.6
Classifier: Programming Language :: Python :: Implementation :: CPython
Classifier: Programming Language :: Python :: Implementation :: PyPy
Requires-Python: >=3.6.0
Dynamic: author
Dynamic: author-email
Dynamic: classifier
Dynamic: description
Dynamic: description-content-type
Dynamic: keywords
Dynamic: license
Dynamic: requires-python
Dynamic: summary
